[
  {
    "line": 1,
    "elements": [
      {
        "line": 3,
        "name": "Login with incorrect username and correct password",
        "description": "",
        "id": "crm-application-testing;login-with-incorrect-username-and-correct-password",
        "type": "scenario",
        "keyword": "Scenario",
        "steps": [
          {
            "result": {
              "status": "undefined"
            },
            "line": 5,
            "name": "user opens browser",
            "match": {},
            "keyword": "Given "
          },
          {
            "result": {
              "status": "undefined"
            },
            "line": 6,
            "name": "user is on login page",
            "match": {},
            "keyword": "When "
          },
          {
            "result": {
              "status": "undefined"
            },
            "line": 7,
            "name": "user enters username and password",
            "match": {},
            "keyword": "Then "
          },
          {
            "result": {
              "status": "undefined"
            },
            "line": 8,
            "name": "user page is displayed",
            "match": {},
            "keyword": "Then "
          },
          {
            "result": {
              "status": "undefined"
            },
            "line": 9,
            "name": "validate home page title",
            "match": {},
            "keyword": "Then "
          },
          {
            "result": {
              "status": "undefined"
            },
            "line": 10,
            "name": "validate logged in username",
            "match": {},
            "keyword": "Then "
          }
        ]
      }
    ],
    "name": "CRM application testing",
    "description": "",
    "id": "crm-application-testing",
    "keyword": "Feature",
    "uri": "C:/Workspace/BDDFramework/CucumberPOM/src/main/java/com/qa/features/crm.feature"
  }
]